[
    {
        "label": "Person",
        "normalizedVertices": [
            {
                "x": 0.5874634,
                "y": 0.19457385
            },
            {
                "x": 0.7431249,
                "y": 0.19457385
            },
            {
                "x": 0.7431249,
                "y": 0.5760144
            },
            {
                "x": 0.5874634,
                "y": 0.5760144
            }
        ],
        "score": 0.6290749
    },
    {
        "label": "Picture frame",
        "normalizedVertices": [
            {
                "x": 0.0034017898,
                "y": 0.29700294
            },
            {
                "x": 0.24812764,
                "y": 0.29700294
            },
            {
                "x": 0.24812764,
                "y": 0.86982065
            },
            {
                "x": 0.0034017898,
                "y": 0.86982065
            }
        ],
        "score": 0.5474117
    }
]