[
    {
        "label": "Animal",
        "normalizedVertices": [
            {
                "x": 0.6436801,
                "y": 0.49795157
            },
            {
                "x": 0.8426357,
                "y": 0.49795157
            },
            {
                "x": 0.8426357,
                "y": 0.59554696
            },
            {
                "x": 0.6436801,
                "y": 0.59554696
            }
        ],
        "score": 0.59249896
    },
    {
        "label": "Animal",
        "normalizedVertices": [
            {
                "x": 0.6211662,
                "y": 0.6487875
            },
            {
                "x": 0.8337688,
                "y": 0.6487875
            },
            {
                "x": 0.8337688,
                "y": 0.7572064
            },
            {
                "x": 0.6211662,
                "y": 0.7572064
            }
        ],
        "score": 0.5201238
    }
]