[
    {
        "label": "Animal",
        "normalizedVertices": [
            {
                "x": 0.40029413,
                "y": 0.33079568
            },
            {
                "x": 0.56111765,
                "y": 0.33079568
            },
            {
                "x": 0.56111765,
                "y": 0.49867797
            },
            {
                "x": 0.40029413,
                "y": 0.49867797
            }
        ],
        "score": 0.5662352
    },
    {
        "label": "Animal",
        "normalizedVertices": [
            {
                "x": 0.28376472,
                "y": 0.56
            },
            {
                "x": 0.5847059,
                "y": 0.56
            },
            {
                "x": 0.5847059,
                "y": 0.81294125
            },
            {
                "x": 0.28376472,
                "y": 0.81294125
            }
        ],
        "score": 0.5039379
    }
]