[
    {
        "label": "Musical instrument",
        "normalizedVertices": [
            {
                "x": 0.09575035,
                "y": 0.08581634
            },
            {
                "x": 0.5562497,
                "y": 0.08581634
            },
            {
                "x": 0.5562497,
                "y": 0.37841895
            },
            {
                "x": 0.09575035,
                "y": 0.37841895
            }
        ],
        "score": 0.61322445
    },
    {
        "label": "Flower",
        "normalizedVertices": [
            {
                "x": 0.44971234,
                "y": 0.57812285
            },
            {
                "x": 0.71940225,
                "y": 0.57812285
            },
            {
                "x": 0.71940225,
                "y": 0.7296666
            },
            {
                "x": 0.44971234,
                "y": 0.7296666
            }
        ],
        "score": 0.580117
    },
    {
        "label": "Animal",
        "normalizedVertices": [
            {
                "x": 0.16022094,
                "y": 0.68040454
            },
            {
                "x": 0.54777914,
                "y": 0.68040454
            },
            {
                "x": 0.54777914,
                "y": 0.88406605
            },
            {
                "x": 0.16022094,
                "y": 0.88406605
            }
        ],
        "score": 0.5478354
    }
]