[
    {
        "label": "Person",
        "normalizedVertices": [
            {
                "x": 0.14087516,
                "y": 0.017867949
            },
            {
                "x": 0.3727719,
                "y": 0.017867949
            },
            {
                "x": 0.3727719,
                "y": 0.40213203
            },
            {
                "x": 0.14087516,
                "y": 0.40213203
            }
        ],
        "score": 0.8640498
    },
    {
        "label": "Hat",
        "normalizedVertices": [
            {
                "x": 0.12270301,
                "y": 0.007175505
            },
            {
                "x": 0.3829812,
                "y": 0.007175505
            },
            {
                "x": 0.3829812,
                "y": 0.11589569
            },
            {
                "x": 0.12270301,
                "y": 0.11589569
            }
        ],
        "score": 0.65092427
    }
]