[
    {
        "label": "Grape",
        "normalizedVertices": [
            {
                "x": 0.27163267,
                "y": 0.06797119
            },
            {
                "x": 0.70295554,
                "y": 0.06797119
            },
            {
                "x": 0.70295554,
                "y": 0.92544055
            },
            {
                "x": 0.27163267,
                "y": 0.92544055
            }
        ],
        "score": 0.73265374
    },
    {
        "label": "Fruit",
        "normalizedVertices": [
            {
                "x": 0.27163267,
                "y": 0.06797119
            },
            {
                "x": 0.70295554,
                "y": 0.06797119
            },
            {
                "x": 0.70295554,
                "y": 0.92544055
            },
            {
                "x": 0.27163267,
                "y": 0.92544055
            }
        ],
        "score": 0.7262339
    }
]