[
    {
        "label": "Seahorse",
        "normalizedVertices": [
            {
                "x": 0.79104394,
                "y": 0.0502691
            },
            {
                "x": 0.9929561,
                "y": 0.0502691
            },
            {
                "x": 0.9929561,
                "y": 0.94973093
            },
            {
                "x": 0.79104394,
                "y": 0.94973093
            }
        ],
        "score": 0.5419886
    },
    {
        "label": "Animal",
        "normalizedVertices": [
            {
                "x": 0.79104394,
                "y": 0.0502691
            },
            {
                "x": 0.9929561,
                "y": 0.0502691
            },
            {
                "x": 0.9929561,
                "y": 0.94973093
            },
            {
                "x": 0.79104394,
                "y": 0.94973093
            }
        ],
        "score": 0.5363562
    }
]