[
    {
        "label": "Person",
        "normalizedVertices": [
            {
                "x": 0.8281808,
                "y": 0.5512043
            },
            {
                "x": 0.91242605,
                "y": 0.5512043
            },
            {
                "x": 0.91242605,
                "y": 0.88726014
            },
            {
                "x": 0.8281808,
                "y": 0.88726014
            }
        ],
        "score": 0.87096494
    },
    {
        "label": "Person",
        "normalizedVertices": [
            {
                "x": 0.4809362,
                "y": 0.5451609
            },
            {
                "x": 0.5392991,
                "y": 0.5451609
            },
            {
                "x": 0.5392991,
                "y": 0.78427565
            },
            {
                "x": 0.4809362,
                "y": 0.78427565
            }
        ],
        "score": 0.7723787
    },
    {
        "label": "Person",
        "normalizedVertices": [
            {
                "x": 0.32492378,
                "y": 0.5343374
            },
            {
                "x": 0.38893378,
                "y": 0.5343374
            },
            {
                "x": 0.38893378,
                "y": 0.7809815
            },
            {
                "x": 0.32492378,
                "y": 0.7809815
            }
        ],
        "score": 0.7259665
    },
    {
        "label": "Person",
        "normalizedVertices": [
            {
                "x": 0.27135104,
                "y": 0.534808
            },
            {
                "x": 0.33065516,
                "y": 0.534808
            },
            {
                "x": 0.33065516,
                "y": 0.7753344
            },
            {
                "x": 0.27135104,
                "y": 0.7753344
            }
        ],
        "score": 0.6851925
    },
    {
        "label": "Person",
        "normalizedVertices": [
            {
                "x": 0.13926436,
                "y": 0.5366161
            },
            {
                "x": 0.21739198,
                "y": 0.5366161
            },
            {
                "x": 0.21739198,
                "y": 0.8999661
            },
            {
                "x": 0.13926436,
                "y": 0.8999661
            }
        ],
        "score": 0.61710066
    }
]