[
    {
        "label": "Plate",
        "normalizedVertices": [
            {
                "x": 0.51482356,
                "y": 0.017647061
            },
            {
                "x": 0.8600001,
                "y": 0.017647061
            },
            {
                "x": 0.8600001,
                "y": 0.35764706
            },
            {
                "x": 0.51482356,
                "y": 0.35764706
            }
        ],
        "score": 0.70044684
    },
    {
        "label": "Tableware",
        "normalizedVertices": [
            {
                "x": 0.51482356,
                "y": 0.017647061
            },
            {
                "x": 0.8600001,
                "y": 0.017647061
            },
            {
                "x": 0.8600001,
                "y": 0.35764706
            },
            {
                "x": 0.51482356,
                "y": 0.35764706
            }
        ],
        "score": 0.52243334
    }
]