[
    {
        "label": "Animal",
        "normalizedVertices": [
            {
                "x": 0.47786796,
                "y": 0.08393398
            },
            {
                "x": 0.95624965,
                "y": 0.08393398
            },
            {
                "x": 0.95624965,
                "y": 0.37794837
            },
            {
                "x": 0.47786796,
                "y": 0.37794837
            }
        ],
        "score": 0.68371373
    },
    {
        "label": "Person",
        "normalizedVertices": [
            {
                "x": 0.50704443,
                "y": 0.683934
            },
            {
                "x": 0.9487202,
                "y": 0.683934
            },
            {
                "x": 0.9487202,
                "y": 0.9755955
            },
            {
                "x": 0.50704443,
                "y": 0.9755955
            }
        ],
        "score": 0.5300885
    }
]