[
    {
        "label": "Coin",
        "normalizedVertices": [
            {
                "x": 0.1326255,
                "y": 0.5877245
            },
            {
                "x": 0.7840804,
                "y": 0.5877245
            },
            {
                "x": 0.7840804,
                "y": 0.9190991
            },
            {
                "x": 0.1326255,
                "y": 0.9190991
            }
        ],
        "score": 0.597154
    },
    {
        "label": "Coin",
        "normalizedVertices": [
            {
                "x": 0.097867966,
                "y": 0.21405163
            },
            {
                "x": 0.46895558,
                "y": 0.21405163
            },
            {
                "x": 0.46895558,
                "y": 0.41818368
            },
            {
                "x": 0.097867966,
                "y": 0.41818368
            }
        ],
        "score": 0.54400146
    }
]