[
    {
        "label": "Bag",
        "normalizedVertices": [
            {
                "x": 0.1301924,
                "y": 0.033985697
            },
            {
                "x": 0.7189841,
                "y": 0.033985697
            },
            {
                "x": 0.7189841,
                "y": 0.29660255
            },
            {
                "x": 0.1301924,
                "y": 0.29660255
            }
        ],
        "score": 0.7670544
    },
    {
        "label": "Hat",
        "normalizedVertices": [
            {
                "x": 0.11604047,
                "y": 0.5457266
            },
            {
                "x": 0.47420102,
                "y": 0.5457266
            },
            {
                "x": 0.47420102,
                "y": 0.6756233
            },
            {
                "x": 0.11604047,
                "y": 0.6756233
            }
        ],
        "score": 0.55808264
    }
]