[
    {
        "label": "Plate",
        "normalizedVertices": [
            {
                "x": 0.4644706,
                "y": 0.0035294152
            },
            {
                "x": 0.8600001,
                "y": 0.0035294152
            },
            {
                "x": 0.8600001,
                "y": 0.33741176
            },
            {
                "x": 0.4644706,
                "y": 0.33741176
            }
        ],
        "score": 0.85225403
    },
    {
        "label": "Kitchenware",
        "normalizedVertices": [
            {
                "x": 0.4644706,
                "y": 0.0035294152
            },
            {
                "x": 0.8600001,
                "y": 0.0035294152
            },
            {
                "x": 0.8600001,
                "y": 0.33741176
            },
            {
                "x": 0.4644706,
                "y": 0.33741176
            }
        ],
        "score": 0.7075945
    },
    {
        "label": "Tableware",
        "normalizedVertices": [
            {
                "x": 0.4644706,
                "y": 0.0035294152
            },
            {
                "x": 0.8600001,
                "y": 0.0035294152
            },
            {
                "x": 0.8600001,
                "y": 0.33741176
            },
            {
                "x": 0.4644706,
                "y": 0.33741176
            }
        ],
        "score": 0.60815716
    }
]