[
    {
        "label": "Person",
        "normalizedVertices": [
            {
                "x": 0.28760415,
                "y": 0.09092687
            },
            {
                "x": 0.82227826,
                "y": 0.09092687
            },
            {
                "x": 0.82227826,
                "y": 0.28766137
            },
            {
                "x": 0.28760415,
                "y": 0.28766137
            }
        ],
        "score": 0.6708141
    },
    {
        "label": "Woman",
        "normalizedVertices": [
            {
                "x": 0.28760415,
                "y": 0.09092687
            },
            {
                "x": 0.82227826,
                "y": 0.09092687
            },
            {
                "x": 0.82227826,
                "y": 0.28766137
            },
            {
                "x": 0.28760415,
                "y": 0.28766137
            }
        ],
        "score": 0.6287404
    },
    {
        "label": "Person",
        "normalizedVertices": [
            {
                "x": 0.28760415,
                "y": 0.09092687
            },
            {
                "x": 0.82227826,
                "y": 0.09092687
            },
            {
                "x": 0.82227826,
                "y": 0.28766137
            },
            {
                "x": 0.28760415,
                "y": 0.28766137
            }
        ],
        "score": 0.5618323
    }
]