[
    {
        "label": "Man",
        "normalizedVertices": [
            {
                "x": 0.3925399,
                "y": 0.5836006
            },
            {
                "x": 0.4725499,
                "y": 0.5836006
            },
            {
                "x": 0.4725499,
                "y": 0.9083623
            },
            {
                "x": 0.3925399,
                "y": 0.9083623
            }
        ],
        "score": 0.66566294
    },
    {
        "label": "Person",
        "normalizedVertices": [
            {
                "x": 0.23840988,
                "y": 0.59112996
            },
            {
                "x": 0.31841984,
                "y": 0.59112996
            },
            {
                "x": 0.31841984,
                "y": 0.9215388
            },
            {
                "x": 0.23840988,
                "y": 0.9215388
            }
        ],
        "score": 0.65601826
    },
    {
        "label": "Person",
        "normalizedVertices": [
            {
                "x": 0.49450898,
                "y": 0.7156873
            },
            {
                "x": 0.63287187,
                "y": 0.7156873
            },
            {
                "x": 0.63287187,
                "y": 0.986802
            },
            {
                "x": 0.49450898,
                "y": 0.986802
            }
        ],
        "score": 0.6369132
    },
    {
        "label": "Person",
        "normalizedVertices": [
            {
                "x": 0.3925399,
                "y": 0.5836006
            },
            {
                "x": 0.4725499,
                "y": 0.5836006
            },
            {
                "x": 0.4725499,
                "y": 0.9083623
            },
            {
                "x": 0.3925399,
                "y": 0.9083623
            }
        ],
        "score": 0.6211213
    },
    {
        "label": "Person",
        "normalizedVertices": [
            {
                "x": 0.721805,
                "y": 0.8387585
            },
            {
                "x": 0.8261579,
                "y": 0.8387585
            },
            {
                "x": 0.8261579,
                "y": 0.9840526
            },
            {
                "x": 0.721805,
                "y": 0.9840526
            }
        ],
        "score": 0.5708574
    }
]