[
    {
        "label": "Bird",
        "normalizedVertices": [
            {
                "x": 0.41111767,
                "y": 0.39229414
            },
            {
                "x": 0.61335295,
                "y": 0.39229414
            },
            {
                "x": 0.61335295,
                "y": 0.57288235
            },
            {
                "x": 0.41111767,
                "y": 0.57288235
            }
        ],
        "score": 0.744277
    },
    {
        "label": "Animal",
        "normalizedVertices": [
            {
                "x": 0.41111767,
                "y": 0.39229414
            },
            {
                "x": 0.61335295,
                "y": 0.39229414
            },
            {
                "x": 0.61335295,
                "y": 0.57288235
            },
            {
                "x": 0.41111767,
                "y": 0.57288235
            }
        ],
        "score": 0.5445415
    }
]