[
    {
        "label": "Person",
        "normalizedVertices": [
            {
                "x": 0.35905883,
                "y": 0.6218824
            },
            {
                "x": 0.5964706,
                "y": 0.6218824
            },
            {
                "x": 0.5964706,
                "y": 0.89647055
            },
            {
                "x": 0.35905883,
                "y": 0.89647055
            }
        ],
        "score": 0.6957112
    },
    {
        "label": "Person",
        "normalizedVertices": [
            {
                "x": 0.63169783,
                "y": 0.43605876
            },
            {
                "x": 0.78511953,
                "y": 0.43605876
            },
            {
                "x": 0.78511953,
                "y": 0.78482056
            },
            {
                "x": 0.63169783,
                "y": 0.78482056
            }
        ],
        "score": 0.5300885
    }
]