[
    {
        "label": "Person",
        "normalizedVertices": [
            {
                "x": 0.68628615,
                "y": 0.46617642
            },
            {
                "x": 0.75970775,
                "y": 0.46617642
            },
            {
                "x": 0.75970775,
                "y": 0.7448205
            },
            {
                "x": 0.68628615,
                "y": 0.7448205
            }
        ],
        "score": 0.67444724
    },
    {
        "label": "Horse",
        "normalizedVertices": [
            {
                "x": 0.10016928,
                "y": 0.5550444
            },
            {
                "x": 0.27936015,
                "y": 0.5550444
            },
            {
                "x": 0.27936015,
                "y": 0.96095556
            },
            {
                "x": 0.10016928,
                "y": 0.96095556
            }
        ],
        "score": 0.60562915
    },
    {
        "label": "Person",
        "normalizedVertices": [
            {
                "x": 0.5363914,
                "y": 0.46005875
            },
            {
                "x": 0.6004013,
                "y": 0.46005875
            },
            {
                "x": 0.6004013,
                "y": 0.7118793
            },
            {
                "x": 0.5363914,
                "y": 0.7118793
            }
        ],
        "score": 0.5206452
    }
]