[
    {
        "label": "Flower",
        "normalizedVertices": [
            {
                "x": 0.46258822,
                "y": 0.25788236
            },
            {
                "x": 0.7498824,
                "y": 0.25788236
            },
            {
                "x": 0.7498824,
                "y": 0.55647063
            },
            {
                "x": 0.46258822,
                "y": 0.55647063
            }
        ],
        "score": 0.8059474
    },
    {
        "label": "Flower",
        "normalizedVertices": [
            {
                "x": 0.17952943,
                "y": 0.3917647
            },
            {
                "x": 0.44141176,
                "y": 0.3917647
            },
            {
                "x": 0.44141176,
                "y": 0.6776471
            },
            {
                "x": 0.17952943,
                "y": 0.6776471
            }
        ],
        "score": 0.789078
    }
]