[
    {
        "label": "Person",
        "normalizedVertices": [
            {
                "x": 0.5548184,
                "y": 0.73960584
            },
            {
                "x": 0.6552373,
                "y": 0.73960584
            },
            {
                "x": 0.6552373,
                "y": 0.92397314
            },
            {
                "x": 0.5548184,
                "y": 0.92397314
            }
        ],
        "score": 0.8994105
    },
    {
        "label": "Tableware",
        "normalizedVertices": [
            {
                "x": 0.14494117,
                "y": 0.13647059
            },
            {
                "x": 0.4331765,
                "y": 0.13647059
            },
            {
                "x": 0.4331765,
                "y": 0.4044706
            },
            {
                "x": 0.14494117,
                "y": 0.4044706
            }
        ],
        "score": 0.5204539
    },
    {
        "label": "Person",
        "normalizedVertices": [
            {
                "x": 0.71380496,
                "y": 0.7626719
            },
            {
                "x": 0.8266285,
                "y": 0.7626719
            },
            {
                "x": 0.8266285,
                "y": 0.9004366
            },
            {
                "x": 0.71380496,
                "y": 0.9004366
            }
        ],
        "score": 0.51105684
    }
]