[
    {
        "label": "Pear",
        "normalizedVertices": [
            {
                "x": 0.36978015,
                "y": 0.69302475
            },
            {
                "x": 0.5593096,
                "y": 0.69302475
            },
            {
                "x": 0.5593096,
                "y": 0.8980836
            },
            {
                "x": 0.36978015,
                "y": 0.8980836
            }
        ],
        "score": 0.7685345
    },
    {
        "label": "Fruit",
        "normalizedVertices": [
            {
                "x": 0.5647771,
                "y": 0.67004025
            },
            {
                "x": 0.7425418,
                "y": 0.67004025
            },
            {
                "x": 0.7425418,
                "y": 0.85533434
            },
            {
                "x": 0.5647771,
                "y": 0.85533434
            }
        ],
        "score": 0.7019758
    },
    {
        "label": "Bird",
        "normalizedVertices": [
            {
                "x": 0.42837876,
                "y": 0.3420083
            },
            {
                "x": 0.55797416,
                "y": 0.3420083
            },
            {
                "x": 0.55797416,
                "y": 0.54896384
            },
            {
                "x": 0.42837876,
                "y": 0.54896384
            }
        ],
        "score": 0.68578243
    },
    {
        "label": "Fruit",
        "normalizedVertices": [
            {
                "x": 0.36978015,
                "y": 0.69302475
            },
            {
                "x": 0.5593096,
                "y": 0.69302475
            },
            {
                "x": 0.5593096,
                "y": 0.8980836
            },
            {
                "x": 0.36978015,
                "y": 0.8980836
            }
        ],
        "score": 0.65409565
    },
    {
        "label": "Food",
        "normalizedVertices": [
            {
                "x": 0.5647771,
                "y": 0.67004025
            },
            {
                "x": 0.7425418,
                "y": 0.67004025
            },
            {
                "x": 0.7425418,
                "y": 0.85533434
            },
            {
                "x": 0.5647771,
                "y": 0.85533434
            }
        ],
        "score": 0.52027076
    }
]