[
    {
        "label": "Bicycle wheel",
        "normalizedVertices": [
            {
                "x": 0.2924532,
                "y": 0.6254829
            },
            {
                "x": 0.38846317,
                "y": 0.6254829
            },
            {
                "x": 0.38846317,
                "y": 0.87777406
            },
            {
                "x": 0.2924532,
                "y": 0.87777406
            }
        ],
        "score": 0.9287395
    },
    {
        "label": "Bicycle",
        "normalizedVertices": [
            {
                "x": 0.29805166,
                "y": 0.4743386
            },
            {
                "x": 0.53136015,
                "y": 0.4743386
            },
            {
                "x": 0.53136015,
                "y": 0.866132
            },
            {
                "x": 0.29805166,
                "y": 0.866132
            }
        ],
        "score": 0.8666306
    },
    {
        "label": "Person",
        "normalizedVertices": [
            {
                "x": 0.80653375,
                "y": 0.086461216
            },
            {
                "x": 0.9034849,
                "y": 0.086461216
            },
            {
                "x": 0.9034849,
                "y": 0.3679289
            },
            {
                "x": 0.80653375,
                "y": 0.3679289
            }
        ],
        "score": 0.7060093
    },
    {
        "label": "Person",
        "normalizedVertices": [
            {
                "x": 0.35799003,
                "y": 0.21629706
            },
            {
                "x": 0.5090688,
                "y": 0.21629706
            },
            {
                "x": 0.5090688,
                "y": 0.74205595
            },
            {
                "x": 0.35799003,
                "y": 0.74205595
            }
        ],
        "score": 0.6816362
    }
]