[
    {
        "label": "Person",
        "normalizedVertices": [
            {
                "x": 0.7516978,
                "y": 0.67662126
            },
            {
                "x": 0.86011666,
                "y": 0.67662126
            },
            {
                "x": 0.86011666,
                "y": 0.88216513
            },
            {
                "x": 0.7516978,
                "y": 0.88216513
            }
        ],
        "score": 0.76347417
    },
    {
        "label": "Animal",
        "normalizedVertices": [
            {
                "x": 0.20341486,
                "y": 0.6860403
            },
            {
                "x": 0.38259134,
                "y": 0.6860403
            },
            {
                "x": 0.38259134,
                "y": 0.8783932
            },
            {
                "x": 0.20341486,
                "y": 0.8783932
            }
        ],
        "score": 0.5888926
    },
    {
        "label": "Animal",
        "normalizedVertices": [
            {
                "x": 0.37763268,
                "y": 0.6846398
            },
            {
                "x": 0.73883796,
                "y": 0.6846398
            },
            {
                "x": 0.73883796,
                "y": 0.8868895
            },
            {
                "x": 0.37763268,
                "y": 0.8868895
            }
        ],
        "score": 0.5314719
    }
]