[
    {
        "label": "Person",
        "normalizedVertices": [
            {
                "x": 0.63010275,
                "y": 0.14909263
            },
            {
                "x": 0.84425026,
                "y": 0.14909263
            },
            {
                "x": 0.84425026,
                "y": 0.90502506
            },
            {
                "x": 0.63010275,
                "y": 0.90502506
            }
        ],
        "score": 0.868675
    },
    {
        "label": "Person",
        "normalizedVertices": [
            {
                "x": 0.10034296,
                "y": 0.4073559
            },
            {
                "x": 0.25942177,
                "y": 0.4073559
            },
            {
                "x": 0.25942177,
                "y": 0.95429134
            },
            {
                "x": 0.10034296,
                "y": 0.95429134
            }
        ],
        "score": 0.8546155
    },
    {
        "label": "Woman",
        "normalizedVertices": [
            {
                "x": 0.63010275,
                "y": 0.14909263
            },
            {
                "x": 0.84425026,
                "y": 0.14909263
            },
            {
                "x": 0.84425026,
                "y": 0.90502506
            },
            {
                "x": 0.63010275,
                "y": 0.90502506
            }
        ],
        "score": 0.7525665
    },
    {
        "label": "Table",
        "normalizedVertices": [
            {
                "x": 0.26582354,
                "y": 0.45358828
            },
            {
                "x": 0.665,
                "y": 0.45358828
            },
            {
                "x": 0.665,
                "y": 0.93888235
            },
            {
                "x": 0.26582354,
                "y": 0.93888235
            }
        ],
        "score": 0.6283834
    }
]