[
    {
        "label": "Person",
        "normalizedVertices": [
            {
                "x": 0.030102689,
                "y": 0.11897499
            },
            {
                "x": 0.28989732,
                "y": 0.11897499
            },
            {
                "x": 0.28989732,
                "y": 0.94973093
            },
            {
                "x": 0.030102689,
                "y": 0.94973093
            }
        ],
        "score": 0.7723787
    },
    {
        "label": "Person",
        "normalizedVertices": [
            {
                "x": 0.32151946,
                "y": 0.53512055
            },
            {
                "x": 0.41942176,
                "y": 0.53512055
            },
            {
                "x": 0.41942176,
                "y": 0.9855853
            },
            {
                "x": 0.32151946,
                "y": 0.9855853
            }
        ],
        "score": 0.60071915
    }
]