[
    {
        "label": "Person",
        "normalizedVertices": [
            {
                "x": 0.291512,
                "y": 0.37314853
            },
            {
                "x": 0.36022788,
                "y": 0.37314853
            },
            {
                "x": 0.36022788,
                "y": 0.637675
            },
            {
                "x": 0.291512,
                "y": 0.637675
            }
        ],
        "score": 0.82735443
    },
    {
        "label": "Person",
        "normalizedVertices": [
            {
                "x": 0.21260183,
                "y": 0.378325
            },
            {
                "x": 0.2813177,
                "y": 0.378325
            },
            {
                "x": 0.2813177,
                "y": 0.64238083
            },
            {
                "x": 0.21260183,
                "y": 0.64238083
            }
        ],
        "score": 0.82218146
    },
    {
        "label": "Person",
        "normalizedVertices": [
            {
                "x": 0.067809254,
                "y": 0.36891323
            },
            {
                "x": 0.1657016,
                "y": 0.36891323
            },
            {
                "x": 0.1657016,
                "y": 0.6372044
            },
            {
                "x": 0.067809254,
                "y": 0.6372044
            }
        ],
        "score": 0.7292123
    }
]